{"advice":"避免在可公网路由子网部署Redis并收敛安全组来源，禁止0.0.0.0/0或::/0访问Redis端口。","categoryList":["网络访问"],"code":"AWS_ElastiCache_202602261520_900044","context":"集群：{$.CacheCluster.CacheClusterId}\n子网组：{$.NetworkExposure.CacheSubnetGroupName}","description":"ElastiCache Redis同时满足公网可达链路（IGW路由+公共子网）与安全组对公网放通Redis端口/全流量。","level":"High","link":"https://docs.aws.amazon.com/AmazonElastiCache/latest/dg/accessing-elasticache.html","linkedDataList":null,"name":"AWS-ElastiCache-全流量放通且公网可达","platform":"AWS","resourceType":"ElastiCache"}
